chronos/__init__.py
chronos_python-1.0.0.data/scripts/chronos-nagios.py
chronos_python-1.0.0.data/scripts/chronos-sync-jobs.py
chronos_python-1.0.0.dist-info/DESCRIPTION.rst
chronos_python-1.0.0.dist-info/METADATA
chronos_python-1.0.0.dist-info/RECORD
chronos_python-1.0.0.dist-info/WHEEL
chronos_python-1.0.0.dist-info/metadata.json
chronos_python-1.0.0.dist-info/top_level.txt
