Metadata-Version: 2.0
Name: chronos-python
Version: 1.0.0
Summary: A Python client libary for the Chronos Job Scheduler.
Home-page: https://github.com/asher/chronos-python
Author: Asher Feldman
Author-email: asher@democument.com
License: MIT
Keywords: chronos
Platform: UNKNOWN
Classifier: Development Status :: 3 - Alpha
Classifier: Topic :: Software Development :: Libraries :: Python Modules
Classifier: License :: OSI Approved :: MIT License
Requires-Dist: httplib2 (>=0.9)
